assembly_theory-0.6.0.dist-info/METADATA
assembly_theory-0.6.0.dist-info/WHEEL
assembly_theory-0.6.0.dist-info/licenses/LICENSE-APACHE
assembly_theory-0.6.0.dist-info/licenses/LICENSE-MIT
assembly_theory/__init__.py
assembly_theory/assembly_theory.abi3.so
assembly_theory-0.6.0.dist-info/RECORD
