Metadata-Version: 2.4
Name: assembly-theory
Version: 0.6.0
License-File: LICENSE-APACHE
License-File: LICENSE-MIT
Summary: Open, reproducible calculation of assembly indices
Author-email: Devansh Vimal <dvpatel5@asu.edu>, Garrett Parzych <gparzych@asu.edu>, Joshua Daymude <jdaymude@asu.edu>, Cole Mathis <cole.mathis@asu.edu>
Maintainer-email: Devansh Vimal <dvpatel5@asu.edu>, Garrett Parzych <gparzych@asu.edu>, Joshua Daymude <jdaymude@asu.edu>, Cole Mathis <cole.mathis@asu.edu>
License: MIT OR Apache-2.0
Requires-Python: >=3.10
Project-URL: Repository, https://github.com/DaymudeLab/assembly-theory
Project-URL: Documentation, https://docs.rs/assembly-theory/latest/assembly_theory/python
